README.md
setup.py
pysenti/__init__.py
pysenti/__main__.py
pysenti/bayes.py
pysenti/compat.py
pysenti/frequency.py
pysenti/model_classifier.py
pysenti/rule_classfier.py
pysenti/tokenizer.py
pysenti/train.py
pysenti/utils.py
pysenti.egg-info/PKG-INFO
pysenti.egg-info/SOURCES.txt
pysenti.egg-info/dependency_links.txt
pysenti.egg-info/requires.txt
pysenti.egg-info/top_level.txt
pysenti/../README.md
pysenti/data/adverb_dict.txt
pysenti/data/conjunction_dict.txt
pysenti/data/denial_dict.txt
pysenti/data/neg_sentences.txt
pysenti/data/pos_sentences.txt
pysenti/data/process.py
pysenti/data/sentiment_dict.txt
pysenti/data/sentiment_model.pkl
pysenti/data/stopwords.txt