Metadata-Version: 2.1
Name: pysenti
Version: 0.1.8
Summary: Chinese Sentiment Classifier
Home-page: https://github.com/shibing624/pysenti
Author: XuMing
Author-email: xuming624@qq.com
License: Apache 2.0
Keywords: NLP,sentiment-classifier,sentiment-classification,pysenti
Platform: UNKNOWN
Classifier: Intended Audience :: Developers
Classifier: Operating System :: OS Independent
Classifier: Natural Language :: Chinese (Simplified)
Classifier: Natural Language :: Chinese (Traditional)
Classifier: Programming Language :: Python
Classifier: Programming Language :: Python :: 2
Classifier: Programming Language :: Python :: 2.7
Classifier: Programming Language :: Python :: 3
Classifier: Topic :: Text Processing
Classifier: Topic :: Text Processing :: Indexing
Classifier: Topic :: Text Processing :: Linguistic
